Ani_mail/EmailManager.py
ANI_MAIL-1.0.2.dist-info/LICENSE
ANI_MAIL-1.0.2.dist-info/METADATA
ANI_MAIL-1.0.2.dist-info/WHEEL
ANI_MAIL-1.0.2.dist-info/entry_points.txt
ANI_MAIL-1.0.2.dist-info/top_level.txt
ANI_MAIL-1.0.2.dist-info/RECORD
