Metadata-Version: 2.1
Name: ANI-MAIL
Version: 1.0.2
Summary: A Python package to send mail one person or more than one person, read mail, clear inbox, clear trash box and you can mail bomb as well.
Home-page: https://github.com/aniket-coder-arch/Email_Manager
Author: Aniket Dubey
Author-email: daniket182@gmail.com
License: MIT
Platform: UNKNOWN
Classifier: License :: OSI Approved :: MIT License
Classifier: Programming Language :: Python :: 3
Classifier: Programming Language :: Python :: 3.7
